[
  {
    "id": 4,
    "name": "تحاليل طبية",
    "name_ar": "تحاليل طبية",
    "code": "CAT-LAB"
  },
  {
    "id": 5,
    "name": "اسنان وقائي",
    "name_ar": "اسنان وقائي",
    "code": "CAT-DENT-PREV"
  },
  {
    "id": 6,
    "name": "اسنان تجميلي",
    "name_ar": "اسنان تجميلي",
    "code": "CAT-DENT-COS"
  },
  {
    "id": 7,
    "name": "اشعة",
    "name_ar": "اشعة",
    "code": "CAT-RAD"
  },
  {
    "id": 8,
    "name": "علاج طبيعي",
    "name_ar": "علاج طبيعي",
    "code": "CAT-PHYSIO"
  },
  {
    "id": 2,
    "name": "إيواء",
    "name_ar": "إيواء",
    "code": "CAT-INPAT"
  },
  {
    "id": 3,
    "name": "عيادات خارجية",
    "name_ar": "عيادات خارجية",
    "code": "CAT-OUTPAT"
  },
  {
    "id": 1,
    "name": "عمليات",
    "name_ar": "عمليات",
    "code": "CAT-OPER"
  },
  {
    "id": 9,
    "name": "جراحة عامة - إيواء",
    "name_ar": "جراحة عامة - إيواء",
    "code": "CAT-IP-GS"
  },
  {
    "id": 10,
    "name": "أوعية دموية - إيواء",
    "name_ar": "أوعية دموية - إيواء",
    "code": "CAT-IP-VASC"
  },
  {
    "id": 11,
    "name": "قلب وقسطرة - إيواء",
    "name_ar": "قلب وقسطرة - إيواء",
    "code": "CAT-IP-CARD"
  },
  {
    "id": 12,
    "name": "نساء وولادة - إيواء",
    "name_ar": "نساء وولادة - إيواء",
    "code": "CAT-IP-OB"
  },
  {
    "id": 13,
    "name": "علاج أورام - إيواء",
    "name_ar": "علاج أورام - إيواء",
    "code": "CAT-IP-ONCO"
  },
  {
    "id": 14,
    "name": "غسيل كلى - إيواء",
    "name_ar": "غسيل كلى - إيواء",
    "code": "CAT-IP-DIAL"
  },
  {
    "id": 15,
    "name": "عناية فائقة - إيواء",
    "name_ar": "عناية فائقة - إيواء",
    "code": "CAT-IP-ICU"
  },
  {
    "id": 16,
    "name": "غرفة عمليات - عامة",
    "name_ar": "غرفة عمليات - عامة",
    "code": "CAT-OR-GEN"
  },
  {
    "id": 17,
    "name": "غرفة عمليات - أوعية دموية",
    "name_ar": "غرفة عمليات - أوعية دموية",
    "code": "CAT-OR-VASC"
  },
  {
    "id": 18,
    "name": "غرفة عمليات - تجميل",
    "name_ar": "غرفة عمليات - تجميل",
    "code": "CAT-OR-PLAST"
  },
  {
    "id": 19,
    "name": "كشف وزيارات - عيادة",
    "name_ar": "كشف وزيارات - عيادة",
    "code": "CAT-OP-CONS"
  },
  {
    "id": 20,
    "name": "تحاليل ومختبرات - عيادة",
    "name_ar": "تحاليل ومختبرات - عيادة",
    "code": "CAT-OP-LAB"
  },
  {
    "id": 21,
    "name": "أشعة تخصصية - عيادة",
    "name_ar": "أشعة تخصصية - عيادة",
    "code": "CAT-OP-IMG"
  },
  {
    "id": 22,
    "name": "علاج طبيعي - عيادة",
    "name_ar": "علاج طبيعي - عيادة",
    "code": "CAT-OP-PHYS"
  },
  {
    "id": 23,
    "name": "أسنان - عيادة",
    "name_ar": "أسنان - عيادة",
    "code": "CAT-OP-DENT"
  },
  {
    "id": 24,
    "name": "نظارات طبية - عيادة",
    "name_ar": "نظارات طبية - عيادة",
    "code": "CAT-OP-OPT"
  },
  {
    "id": 25,
    "name": "أدوية بوصفة - عيادة",
    "name_ar": "أدوية بوصفة - عيادة",
    "code": "CAT-OP-DRUG"
  },
  {
    "id": 26,
    "name": "علاج ألم - عيادة",
    "name_ar": "علاج ألم - عيادة",
    "code": "CAT-OP-PAIN"
  },
  {
    "id": 27,
    "name": "إسعاف محلي - طوارئ",
    "name_ar": "إسعاف محلي - طوارئ",
    "code": "CAT-EM-AMB"
  },
  {
    "id": 28,
    "name": "إخلاء طبي - طوارئ",
    "name_ar": "إخلاء طبي - طوارئ",
    "code": "CAT-EM-EVAC"
  },
  {
    "id": 29,
    "name": "أدوية مزمنة - منافع خاصة",
    "name_ar": "أدوية مزمنة - منافع خاصة",
    "code": "CAT-SP-CHR"
  },
  {
    "id": 30,
    "name": "إصابات عمل - منافع خاصة",
    "name_ar": "إصابات عمل - منافع خاصة",
    "code": "CAT-SP-OCC"
  },
  {
    "id": 31,
    "name": "طب نفسي - منافع خاصة",
    "name_ar": "طب نفسي - منافع خاصة",
    "code": "CAT-SP-PSY"
  }
]